dagster_pydantic/__init__.py
dagster_pydantic/py.typed
dagster_pydantic/version.py
dagster_pydantic-0.1.0.dist-info/LICENSE
dagster_pydantic-0.1.0.dist-info/WHEEL
dagster_pydantic-0.1.0.dist-info/METADATA
dagster_pydantic-0.1.0.dist-info/RECORD
