Metadata-Version: 2.1
Name: dagster-pydantic
Version: 0.1.0
Summary: 
Author: Mitchell Hynes
Author-email: ecumene@users.noreply.github.com
Requires-Python: >=3.10,<4.0
Classifier: Programming Language :: Python :: 3
Classifier: Programming Language :: Python :: 3.10
Classifier: Programming Language :: Python :: 3.11
Requires-Dist: dagster (>=1.1.7,<2.0.0)
Requires-Dist: pydantic (>=1.10.2,<2.0.0)
